clevermaps_sdk/__init__.py
clevermaps_sdk/accounts.py
clevermaps_sdk/auditlog.py
clevermaps_sdk/client.py
clevermaps_sdk/common.py
clevermaps_sdk/dwh.py
clevermaps_sdk/exceptions.py
clevermaps_sdk/export.py
clevermaps_sdk/jobs.py
clevermaps_sdk/metadata.py
clevermaps_sdk/projects.py
clevermaps_sdk/sdk.py
clevermaps_sdk/search.py
clevermaps_python_sdk-0.1.0.dist-info/METADATA
clevermaps_python_sdk-0.1.0.dist-info/WHEEL
clevermaps_python_sdk-0.1.0.dist-info/RECORD
