Metadata-Version: 2.1
Name: clevermaps-python-sdk
Version: 0.1.0
Summary: "Python SDK client for the CleverMaps REST API"
License: "License :: OSI Approved :: MIT License"
Author: Karel Psota
Author-email: karel.psota@clevermaps.io
Requires-Python: >=3.10,<4.0
Classifier: License :: Other/Proprietary License
Classifier: Programming Language :: Python :: 3
Classifier: Programming Language :: Python :: 3.10
Classifier: Programming Language :: Python :: 3.11
Classifier: Programming Language :: Python :: 3.12
Requires-Dist: pydantic (>=2.0.0)
Requires-Dist: requests (>=2.30.0)
Requires-Dist: tenacity (>=8.2.3)
